{"data":{"propertyOrder":{},"properties":{"referrer":{"name":"referrer","reference":"m:1","cascade":["persist"],"type":"User","owner":true,"array":false},"mobileNumber":{"name":"mobileNumber","reference":"scalar","getter":false,"setter":false,"type":"string","array":false},"status":{"name":"status","reference":"scalar","enum":true,"items":["PENDING","COMPLETED"],"type":"ReferralStatus","array":false}},"props":[{"name":"referrer","reference":"m:1","cascade":["persist"],"type":"User","owner":true,"array":false},{"name":"mobileNumber","reference":"scalar","getter":false,"setter":false,"type":"string","array":false},{"name":"status","reference":"scalar","enum":true,"items":["PENDING","COMPLETED"],"type":"ReferralStatus","array":false}],"primaryKeys":[],"filters":{},"hooks":{},"indexes":[{"properties":"referrer"},{"properties":"mobileNumber"},{"properties":"status"}],"uniques":[],"checks":[],"concurrencyCheckKeys":{},"className":"Referral","path":"./libs/server/util/common/src/lib/@types/classes/entities/referral.entity.ts","name":"Referral","abstract":false,"constructorParams":[],"toJsonParams":[],"extends":"BaseEntity","useCache":true,"relations":[{"name":"referrer","reference":"m:1","cascade":["persist"],"type":"User","owner":true,"array":false}],"collection":"referral"},"origin":"./libs/server/util/common/src/lib/@types/classes/entities/referral.entity.ts","hash":"b38382f197fd33400c1a17d15ca2c4fe","version":"5.7.13"}
